ionpy/Buffer.py
ionpy/Builder.py
ionpy/BuilderCompileOption.py
ionpy/Node.py
ionpy/Param.py
ionpy/Port.py
ionpy/PortMap.py
ionpy/Type.py
ionpy/TypeCode.py
ionpy/__init__.py
ionpy/native.py
ion_kit_python-1.0.0.dist-info/METADATA
ion_kit_python-1.0.0.dist-info/WHEEL
ion_kit_python-1.0.0.dist-info/top_level.txt
ion_kit_python-1.0.0.dist-info/RECORD
