Metadata-Version: 2.1
Name: ion-kit-python
Version: 1.0.0
Summary: Python Binding for ion-kit
Author-email: Takuro Iizuka <t_iizuka@fixstars.com>
Project-URL: Documentation, https://sensing-dev.github.io/doc/
Project-URL: Repository, https://github.com/fixstars/ion-kit
Project-URL: Changelog, https://sensing-dev.github.io/doc/blog/index.html
Classifier: Development Status :: 3 - Alpha
Classifier: Programming Language :: Python
Requires-Python: >=3.8
